hello_atul/__init__.py
hello_atul/main.py
hello_ayush-0.1.0.dist-info/licenses/LICENSE
hello_ayush-0.1.0.dist-info/METADATA
hello_ayush-0.1.0.dist-info/WHEEL
hello_ayush-0.1.0.dist-info/top_level.txt
hello_ayush-0.1.0.dist-info/RECORD
