Metadata-Version: 2.4
Name: hello_ayush
Version: 0.1.0
Summary: A simple package that says hello to Ayush
Home-page: https://github.com/yourusername/hello_ayush
Author: Ayush
Author-email: youremail@example.com
Classifier: Programming Language :: Python :: 3
Classifier: License :: OSI Approved :: MIT License
Classifier: Operating System :: OS Independent
Requires-Python: >=3.6
License-File: LICENSE
Dynamic: author
Dynamic: author-email
Dynamic: classifier
Dynamic: description
Dynamic: description-content-type
Dynamic: home-page
Dynamic: license-file
Dynamic: requires-python
Dynamic: summary
